.gitignore
.travis.yml
MANIFEST.in
README.rst
bootstrap.py
setup.py
travis.cfg
docs/HISTORY.txt
docs/INSTALL.txt
docs/LICENSE.GPL
docs/LICENSE.txt
src/collective/__init__.py
src/collective.geo.contentlocations.egg-info/PKG-INFO
src/collective.geo.contentlocations.egg-info/SOURCES.txt
src/collective.geo.contentlocations.egg-info/dependency_links.txt
src/collective.geo.contentlocations.egg-info/entry_points.txt
src/collective.geo.contentlocations.egg-info/namespace_packages.txt
src/collective.geo.contentlocations.egg-info/not-zip-safe
src/collective.geo.contentlocations.egg-info/requires.txt
src/collective.geo.contentlocations.egg-info/top_level.txt
src/collective/geo/__init__.py
src/collective/geo/contentlocations/README.txt
src/collective/geo/contentlocations/__init__.py
src/collective/geo/contentlocations/config.py
src/collective/geo/contentlocations/configure.zcml
src/collective/geo/contentlocations/events.py
src/collective/geo/contentlocations/geomanager.py
src/collective/geo/contentlocations/geomarker.py
src/collective/geo/contentlocations/geostylemanager.py
src/collective/geo/contentlocations/geostylemanager.txt
src/collective/geo/contentlocations/indexer.py
src/collective/geo/contentlocations/interfaces.py
src/collective/geo/contentlocations/profiles.zcml
src/collective/geo/contentlocations/testing.py
src/collective/geo/contentlocations/upgrades.py
src/collective/geo/contentlocations/utils.py
src/collective/geo/contentlocations/vocabularies.py
src/collective/geo/contentlocations/browser/README.txt
src/collective/geo/contentlocations/browser/__init__.py
src/collective/geo/contentlocations/browser/collectivegeo-loader.gif
src/collective/geo/contentlocations/browser/configure.zcml
src/collective/geo/contentlocations/browser/controlpanel.py
src/collective/geo/contentlocations/browser/geoshapeform.py
src/collective/geo/contentlocations/browser/geostylesform.py
src/collective/geo/contentlocations/browser/helperview.py
src/collective/geo/contentlocations/browser/subform.pt
src/collective/geo/contentlocations/locales/collective.geo.contentlocations.pot
src/collective/geo/contentlocations/locales/rebuild.sh
src/collective/geo/contentlocations/locales/da/LC_MESSAGES/collective.geo.contentlocations.po
src/collective/geo/contentlocations/locales/de/LC_MESSAGES/collective.geo.contentlocations.po
src/collective/geo/contentlocations/locales/es/LC_MESSAGES/collective.geo.contentlocations.po
