Metadata-Version: 1.1
Name: collective.geo.contentlocations
Version: 3.2
Summary: geo reference for plone contents
Home-page: https://github.com/collective/collective.geo.contentlocations
Author: Giorgio Borelli
Author-email: giorgio@giorgioborelli.it
License: GPL
Keywords: Zope Plone GIS KML Google Maps Bing OpenLayers
Platform: UNKNOWN
Classifier: Framework :: Plone
Classifier: Topic :: Internet
Classifier: Topic :: Scientific/Engineering :: GIS
Classifier: Programming Language :: Python
